ckanext/__init__.py
ckanext/drupal_api/__init__.py
ckanext/drupal_api/config.py
ckanext/drupal_api/helpers.py
ckanext/drupal_api/plugin.py
ckanext/drupal_api/types.py
ckanext/drupal_api/utils.py
ckanext/drupal_api/views.py
ckanext/drupal_api/logic/__init__.py
ckanext/drupal_api/logic/api.py
ckanext/drupal_api/templates/drupal_api/config.html
ckanext/drupal_api/tests/__init__.py
ckanext_drupal_api-0.8.1.dist-info/licenses/LICENSE
ckanext_drupal_api-0.8.1.dist-info/METADATA
ckanext_drupal_api-0.8.1.dist-info/WHEEL
ckanext_drupal_api-0.8.1.dist-info/entry_points.txt
ckanext_drupal_api-0.8.1.dist-info/top_level.txt
ckanext_drupal_api-0.8.1.dist-info/RECORD
