Metadata-Version: 2.4
Name: ckanext-drupal-api
Version: 0.8.1
Author-email: DataShades <datashades@linkdigital.com.au>, Sergey Motornyuk <sergey.motornyuk@linkdigital.com.au>
Maintainer-email: DataShades <datashades@linkdigital.com.au>
License: AGPL
Project-URL: Homepage, https://github.com/DataShades/ckanext-drupal-api
Keywords: CKAN
Classifier: Development Status :: 4 - Beta
Classifier: License :: OSI Approved :: GNU Affero General Public License v3 or later (AGPLv3+)
Classifier: Programming Language :: Python :: 3.8
Classifier: Programming Language :: Python :: 3.9
Classifier: Programming Language :: Python :: 3.10
Classifier: Programming Language :: Python :: 3.11
Requires-Python: >=3.8
License-File: LICENSE
Requires-Dist: requests
Provides-Extra: mysql
Requires-Dist: mysqlclient; extra == "mysql"
Dynamic: license-file
